serpentarium/__init__.py
serpentarium/concurrency.py
serpentarium/constants.py
serpentarium/logging.py
serpentarium/multiprocessing_plugin.py
serpentarium/named_plugin_mixin.py
serpentarium/nop.py
serpentarium/plugin.py
serpentarium/plugin_loader.py
serpentarium/plugin_thread_name.py
serpentarium/plugin_wrapper.py
serpentarium/py.typed
serpentarium/types.py
serpentarium-0.6.1.dist-info/LICENSE
serpentarium-0.6.1.dist-info/METADATA
serpentarium-0.6.1.dist-info/WHEEL
serpentarium-0.6.1.dist-info/RECORD
